Metadata-Version: 2.1
Name: newsdataio
Version: 0.0.4
Summary: a unitts driver for ios device, it use AVFoundation.AVSpeechSynthesizer
Home-page: https://github.com/yumoqing/newsdataio
Author: Yu Moqing
Author-email: yumoqing@gmail.com
Keywords: pyttsx,ios,offline tts engine
Classifier: Intended Audience :: End Users/Desktop
Classifier: Intended Audience :: Developers
Classifier: Intended Audience :: Information Technology
Classifier: Intended Audience :: System Administrators
Classifier: Operating System :: OS Independent
Classifier: License :: OSI Approved :: Mozilla Public License 2.0 (MPL 2.0)
Classifier: Programming Language :: Python :: 3
